{
  "parent": "minecraft:recipes/root",
  "rewards": {
    "recipes": [
      "rawmetal:raw_copper_block"
    ]
  },
  "criteria": {
    "has_raw_copper": {
      "trigger": "minecraft:inventory_changed",
      "conditions": {
        "items": [
          {
            "items": [
              "rawmetal:raw_copper"
            ]
          }
        ]
      }
    },
    "has_the_recipe": {
      "trigger": "minecraft:recipe_unlocked",
      "conditions": {
        "recipe": "rawmetal:raw_copper_block"
      }
    }
  },
  "requirements": [
    [
      "has_raw_copper",
      "has_the_recipe"
    ]
  ]
}